reproduci/__init__.py
reproduci/main.py
reproduci/slurm.py
reproduci-0.7.0.dist-info/entry_points.txt
reproduci-0.7.0.dist-info/WHEEL
reproduci-0.7.0.dist-info/METADATA
reproduci-0.7.0.dist-info/RECORD
